DigitalSoul.py
DigitalSoul-1.0.0.dist-info/LICENSE
DigitalSoul-1.0.0.dist-info/METADATA
DigitalSoul-1.0.0.dist-info/WHEEL
DigitalSoul-1.0.0.dist-info/top_level.txt
DigitalSoul-1.0.0.dist-info/RECORD
