Metadata-Version: 2.1
Name: DigitalSoul
Version: 1.0.0
Summary: Unified Compute Platform - CPU, GPU, FPGA, Quantum Computing
Home-page: https://github.com/NeuralDreamResearch/DigitalSoult
Author: Neural Dream Research
Author-email: alihakimxyz@gmail.com
Classifier: Programming Language :: Python :: 3
Classifier: License :: OSI Approved :: MIT License
Classifier: Operating System :: OS Independent
Requires-Python: >=3.8
License-File: LICENSE
